{
	"info": {
		"_postman_id": "044bf1c6-09d2-4856-a7a1-3ae7af401cb2",
		"name": "SalesforceFunctions",
		"schema": "https://schema.getpostman.com/json/collection/v2.1.0/collection.json",
		"_exporter_id": "25389533"
	},
	"item": [
		{
			"name": "Accounts",
			"item": [
				{
					"name": "GET -  Accounts",
					"request": {
						"method": "GET",
						"header": [],
						"url": {
							"raw": "{{baseUrl}}/accounts",
							"host": [
								"{{baseUrl}}"
							],
							"path": [
								"accounts"
							]
						}
					},
					"response": []
				},
				{
					"name": "GET -  Accounts By Id",
					"request": {
						"method": "GET",
						"header": [],
						"url": {
							"raw": "{{baseUrl}}/accounts/id/001gK000002OgxzQAC",
							"host": [
								"{{baseUrl}}"
							],
							"path": [
								"accounts",
								"id",
								"001gK000002OgxzQAC"
							]
						}
					},
					"response": []
				},
				{
					"name": "GET -  Accounts By Filter",
					"request": {
						"method": "GET",
						"header": [],
						"url": {
							"raw": "{{baseUrl}}/accounts/filter/BillingState:CA,British Columbia?isAnd=true",
							"host": [
								"{{baseUrl}}"
							],
							"path": [
								"accounts",
								"filter",
								"BillingState:CA,British Columbia"
							],
							"query": [
								{
									"key": "isAnd",
									"value": "true"
								}
							]
						}
					},
					"response": []
				},
				{
					"name": "POST-  Accounts",
					"request": {
						"method": "POST",
						"header": [],
						"body": {
							"mode": "raw",
							"raw": "[\r\n    {\r\n        \"attributes\": {\r\n            \"type\": \"Account\"\r\n        },\r\n        \"name\": \"CH Test Account Postman 1\",\r\n        \"phone\": \"588-454-5857\",\r\n        \"description\": \"CH Test Account Postman 1 Creation\"\r\n    }\r\n]",
							"options": {
								"raw": {
									"language": "json"
								}
							}
						},
						"url": {
							"raw": "{{baseUrl}}/accounts",
							"host": [
								"{{baseUrl}}"
							],
							"path": [
								"accounts"
							]
						}
					},
					"response": []
				},
				{
					"name": "PATCH -  Accounts",
					"request": {
						"method": "PATCH",
						"header": [],
						"body": {
							"mode": "raw",
							"raw": "[\r\n    {\r\n        \"attributes\": {\r\n            \"type\": \"Account\"\r\n        },\r\n        \"Id\": \"001gK0000040ymfQAA\",\r\n        \"Description\": \"CH Test Account Postman 1 Update\"\r\n    }\r\n]",
							"options": {
								"raw": {
									"language": "json"
								}
							}
						},
						"url": {
							"raw": "{{baseUrl}}/accounts",
							"host": [
								"{{baseUrl}}"
							],
							"path": [
								"accounts"
							]
						}
					},
					"response": []
				},
				{
					"name": "PUT -  Accounts",
					"request": {
						"method": "PUT",
						"header": [],
						"body": {
							"mode": "raw",
							"raw": "[\r\n    {\r\n        \"attributes\": {\r\n            \"type\": \"Account\"\r\n        },\r\n        \"Id\": \"001gK0000040ymfQAA\",\r\n        \"Description\": \"CH Test Account Postman 1 Upsert\"\r\n    },\r\n    {\r\n        \"attributes\": {\r\n            \"type\": \"Account\"\r\n        },\r\n        \"Name\": \"CH Test Account Postman 2\",\r\n        \"Description\": \"CH Test Account Postman 2 New\",\r\n        \"Phone\": \"252-585-6896\"\r\n    }\r\n]",
							"options": {
								"raw": {
									"language": "json"
								}
							}
						},
						"url": {
							"raw": "{{baseUrl}}/accounts/external/Id",
							"host": [
								"{{baseUrl}}"
							],
							"path": [
								"accounts",
								"external",
								"Id"
							]
						}
					},
					"response": []
				}
			]
		},
		{
			"name": "Contacts",
			"item": [
				{
					"name": "GET -  Contacts",
					"request": {
						"method": "GET",
						"header": [],
						"url": {
							"raw": "{{baseUrl}}/contacts",
							"host": [
								"{{baseUrl}}"
							],
							"path": [
								"contacts"
							]
						}
					},
					"response": []
				},
				{
					"name": "GET -  Contacts By Id",
					"request": {
						"method": "GET",
						"header": [],
						"url": {
							"raw": "{{baseUrl}}/contacts/id/003gK000000SYQ9QAO",
							"host": [
								"{{baseUrl}}"
							],
							"path": [
								"contacts",
								"id",
								"003gK000000SYQ9QAO"
							]
						}
					},
					"response": []
				},
				{
					"name": "GET -  Contacts By Filter",
					"request": {
						"method": "GET",
						"header": [],
						"url": {
							"raw": "{{baseUrl}}/contacts/filter/MailingState:KS,CA?isAnd=true",
							"host": [
								"{{baseUrl}}"
							],
							"path": [
								"contacts",
								"filter",
								"MailingState:KS,CA"
							],
							"query": [
								{
									"key": "isAnd",
									"value": "true"
								}
							]
						}
					},
					"response": []
				},
				{
					"name": "POST-  Contacts",
					"request": {
						"method": "POST",
						"header": [],
						"body": {
							"mode": "raw",
							"raw": "[\r\n    {\r\n        \"attributes\": {\r\n            \"type\": \"Contact\"\r\n        },\r\n        \"firstName\": \"CH Test\",\r\n        \"lastName\": \"Contact Five\",\r\n        \"phone\": \"588-454-5857\",\r\n        \"email\": \"chContactFive@email.com\",\r\n        \"description\": \"CH Test Contact 5 Creation\",\r\n        \"mailingStreet\": \"785 Main St\",\r\n        \"mailingCity\": \"Penticton\",\r\n        \"mailingPostalCode\": \"V2A 5E3\",\r\n        \"mailingCountry\": \"Canada\"\r\n    }\r\n]",
							"options": {
								"raw": {
									"language": "json"
								}
							}
						},
						"url": {
							"raw": "{{baseUrl}}/contacts",
							"host": [
								"{{baseUrl}}"
							],
							"path": [
								"contacts"
							]
						}
					},
					"response": []
				},
				{
					"name": "PATCH -  Contacts",
					"request": {
						"method": "PATCH",
						"header": [],
						"body": {
							"mode": "raw",
							"raw": "[\r\n    {\r\n      \"attributes\": {\r\n        \"type\": \"Contact\"\r\n      },\r\n      \"id\": \"003gK000001HOzpQAG\",\r\n      \"description\": \"CH Test Contact 5 Update\"\r\n    }\r\n  ]",
							"options": {
								"raw": {
									"language": "json"
								}
							}
						},
						"url": {
							"raw": "{{baseUrl}}/contacts",
							"host": [
								"{{baseUrl}}"
							],
							"path": [
								"contacts"
							]
						}
					},
					"response": []
				},
				{
					"name": "PUT -  Contacts",
					"request": {
						"method": "PUT",
						"header": [],
						"body": {
							"mode": "raw",
							"raw": "[\r\n  {\r\n    \"attributes\": {\r\n      \"type\": \"Contact\"\r\n    },\r\n    \"id\": \"003gK000001HOzpQAG\",\r\n    \"description\": \"CH Test Contact 5 Upsert\"\r\n  },\r\n  {\r\n    \"attributes\": {\r\n      \"type\": \"Contact\"\r\n    },\r\n    \"firstName\": \"CH Test\",\r\n    \"lastName\": \"Contact Six\",\r\n    \"phone\": \"588-453-2214\",\r\n    \"email\": \"chContactSix@email.com\",\r\n    \"description\": \"CH Test Contact 6 Creation\",\r\n    \"mailingStreet\": \"1000 K. L. O. Rd\",\r\n    \"mailingCity\": \"Kelowna\",\r\n    \"mailingPostalCode\": \"V1Y 4X8\",\r\n    \"mailingCountry\": \"Canada\"\r\n  }\r\n]",
							"options": {
								"raw": {
									"language": "json"
								}
							}
						},
						"url": {
							"raw": "{{baseUrl}}/contacts/external/Id",
							"host": [
								"{{baseUrl}}"
							],
							"path": [
								"contacts",
								"external",
								"Id"
							]
						}
					},
					"response": []
				}
			]
		},
		{
			"name": "Opportunities",
			"item": [
				{
					"name": "GET -  Opportunities",
					"request": {
						"method": "GET",
						"header": [],
						"url": {
							"raw": "{{baseUrl}}/opportunities",
							"host": [
								"{{baseUrl}}"
							],
							"path": [
								"opportunities"
							]
						}
					},
					"response": []
				},
				{
					"name": "GET -  Opportunities By Id",
					"request": {
						"method": "GET",
						"header": [],
						"url": {
							"raw": "{{baseUrl}}/opportunities/id/006gK000000J5DhQAK",
							"host": [
								"{{baseUrl}}"
							],
							"path": [
								"opportunities",
								"id",
								"006gK000000J5DhQAK"
							]
						}
					},
					"response": []
				},
				{
					"name": "GET -  Opportunities By Filter",
					"request": {
						"method": "GET",
						"header": [],
						"url": {
							"raw": "{{baseUrl}}/opportunities/filter/StageName:Closed Won&Type:New Customer?isAnd=true",
							"host": [
								"{{baseUrl}}"
							],
							"path": [
								"opportunities",
								"filter",
								"StageName:Closed Won&Type:New Customer"
							],
							"query": [
								{
									"key": "isAnd",
									"value": "true"
								}
							]
						}
					},
					"response": []
				},
				{
					"name": "POST-  Opportunities",
					"request": {
						"method": "POST",
						"header": [],
						"body": {
							"mode": "raw",
							"raw": "[\r\n    {\r\n        \"attributes\": {\r\n            \"type\": \"Opportunity\"\r\n        },\r\n        \"name\": \"CH Test Opp 2\",\r\n        \"amount\": \"35000\",\r\n        \"description\": \"CH Test Opp 2 Creation\",\r\n        \"stageName\": \"Qualification\",\r\n        \"closeDate\": \"2025-04-15\"\r\n    }\r\n]",
							"options": {
								"raw": {
									"language": "json"
								}
							}
						},
						"url": {
							"raw": "{{baseUrl}}/opportunities",
							"host": [
								"{{baseUrl}}"
							],
							"path": [
								"opportunities"
							]
						}
					},
					"response": []
				},
				{
					"name": "PATCH -  Opportunities",
					"request": {
						"method": "PATCH",
						"header": [],
						"body": {
							"mode": "raw",
							"raw": "[\r\n    {\r\n        \"attributes\": {\r\n            \"type\": \"Opportunity\"\r\n        },\r\n        \"Id\": \"006gK000001KlJxQAK\",\r\n        \"Description\": \"CH Test Opp 2 Update\"\r\n    }\r\n]",
							"options": {
								"raw": {
									"language": "json"
								}
							}
						},
						"url": {
							"raw": "{{baseUrl}}/opportunities",
							"host": [
								"{{baseUrl}}"
							],
							"path": [
								"opportunities"
							]
						}
					},
					"response": []
				},
				{
					"name": "PUT -  Opportunities",
					"request": {
						"method": "PUT",
						"header": [],
						"body": {
							"mode": "raw",
							"raw": "[\r\n  {\r\n    \"attributes\": {\r\n      \"type\": \"Opportunity\"\r\n    },\r\n    \"id\": \"006gK000001KdgHQAS\",\r\n    \"description\": \"CH Test Opp 1 Upsert\",\r\n    \"accountId\": \"001gK00000391O9QAI\"\r\n  },\r\n  {\r\n    \"attributes\": {\r\n      \"type\": \"Opportunity\"\r\n    },\r\n    \"name\": \"CH Test Opp 3\",\r\n    \"description\": \"CH Test Opp 3 New\",\r\n    \"stageName\": \"Needs Analysis\",\r\n    \"closeDate\": \"2025-04-15\",\r\n    \"accountId\": \"001gK00000395JiQAI\"\r\n  }\r\n]",
							"options": {
								"raw": {
									"language": "json"
								}
							}
						},
						"url": {
							"raw": "{{baseUrl}}/opportunities/external/Id",
							"host": [
								"{{baseUrl}}"
							],
							"path": [
								"opportunities",
								"external",
								"Id"
							]
						}
					},
					"response": []
				}
			]
		},
		{
			"name": "GET - Open API",
			"request": {
				"method": "GET",
				"header": [],
				"url": {
					"raw": "{{baseUrl}}/openapi/v3.json",
					"host": [
						"{{baseUrl}}"
					],
					"path": [
						"openapi",
						"v3.json"
					]
				}
			},
			"response": []
		}
	]
}